setup.py
ApiSyncClient/__init__.py
ApiSyncClient/client.py
ApiSyncClient/exception.py
ApiSyncClient/request.py
ApiSyncClient/responce.py
ApiSyncClient.egg-info/PKG-INFO
ApiSyncClient.egg-info/SOURCES.txt
ApiSyncClient.egg-info/dependency_links.txt
ApiSyncClient.egg-info/not-zip-safe
ApiSyncClient.egg-info/top_level.txt