Metadata-Version: 1.1
Name: ApiSyncClient
Version: 1.0
Summary: Client for ApiDaemon-service
Home-page: https://github.com/tsyganov-ivan/ApiDaemon
Author: Ivan Tsyganov
Author-email: tsyganov.ivan@gmail.com
License: MIT-license
Platform: UNKNOWN
Classifier: Natural Language :: English
Classifier: Operating System :: POSIX
Classifier: Programming Language :: Python :: 2.7
